orcx/__init__.py
orcx/cli.py
orcx/config.py
orcx/conversation.py
orcx/errors.py
orcx/py.typed
orcx/registry.py
orcx/router.py
orcx/schema.py
orcx-0.0.6.dist-info/WHEEL
orcx-0.0.6.dist-info/entry_points.txt
orcx-0.0.6.dist-info/METADATA
orcx-0.0.6.dist-info/RECORD
