Metadata-Version: 2.4
Name: orcx
Version: 0.0.6
Summary: LLM orchestrator - route prompts to any model via litellm
Keywords: llm,agents,orchestration,ai,cli,litellm
Author: Nick Russo
Author-email: Nick Russo <nijaru7@gmail.com>
License-Expression: MIT
Classifier: Development Status :: 3 - Alpha
Classifier: Environment :: Console
Classifier: Intended Audience :: Developers
Classifier: License :: OSI Approved :: MIT License
Classifier: Programming Language :: Python :: 3
Classifier: Programming Language :: Python :: 3.11
Classifier: Programming Language :: Python :: 3.12
Classifier: Programming Language :: Python :: 3.13
Classifier: Programming Language :: Python :: 3.14
Classifier: Topic :: Software Development :: Libraries :: Python Modules
Classifier: Typing :: Typed
Requires-Dist: httpx>=0.28.1
Requires-Dist: litellm>=1.80.11
Requires-Dist: pydantic>=2.12.5
Requires-Dist: pyyaml>=6.0.3
Requires-Dist: typer>=0.21.0
Requires-Python: >=3.11
Project-URL: Homepage, https://github.com/nijaru/orcx
Project-URL: Repository, https://github.com/nijaru/orcx
Project-URL: Issues, https://github.com/nijaru/orcx/issues
